py_scm-1.0.1.dist-info/DESCRIPTION.rst
py_scm-1.0.1.dist-info/METADATA
py_scm-1.0.1.dist-info/RECORD
py_scm-1.0.1.dist-info/WHEEL
py_scm-1.0.1.dist-info/metadata.json
py_scm-1.0.1.dist-info/top_level.txt
scm/FrameMover.py
scm/Parallel.py
scm/State.py
scm/StateMachine.py
scm/StateMachineManager.py
scm/__init__.py
