Metadata-Version: 2.0
Name: py-scm
Version: 1.0.1
Summary: A python state machine framework based on statecharts (scxml)
Home-page: https://github.com/zen747/pyscm
Author: Zen Chien
Author-email: jixing.jian@gmail.com
License: Apache License 2.0
Keywords: statecharts,state-machine,scxml,david-harel
Platform: UNKNOWN
Classifier: Development Status :: 5 - Production/Stable
Classifier: Intended Audience :: Developers
Classifier: License :: OSI Approved :: Apache Software License
Classifier: Operating System :: OS Independent
Classifier: Programming Language :: Python
Classifier: Programming Language :: Python :: 3
Classifier: Programming Language :: Python :: 3.6
Classifier: Topic :: Software Development :: Libraries :: Python Modules
Classifier: Topic :: Text Processing :: Linguistic
Requires-Python: >=3.6
